ken_mcp/__init__.py
ken_mcp/__main__.py
ken_mcp/cli.py
ken_mcp/generator.py
ken_mcp/install_checker.py
ken_mcp/mcp_checker.py
ken_mcp/py.typed
ken_mcp/server.py
ken_mcp/core/__init__.py
ken_mcp/core/analyzer.py
ken_mcp/core/models.py
ken_mcp/core/orchestrator.py
ken_mcp/core/requirement_parser.py
ken_mcp/generators/__init__.py
ken_mcp/generators/claude_md.py
ken_mcp/generators/docs.py
ken_mcp/generators/project.py
ken_mcp/generators/server.py
ken_mcp/generators/tests.py
ken_mcp/generators/verification.py
ken_mcp/templates/__init__.py
ken_mcp/templates/constants.py
ken_mcp/templates/diagnostics.py
ken_mcp/utils/__init__.py
ken_mcp/utils/platform.py
ken_mcp/utils/suggestions.py
ken_mcp/utils/text.py
ken_mcp/utils/validation.py
ken_mcp-3.7.5.dist-info/METADATA
ken_mcp-3.7.5.dist-info/WHEEL
ken_mcp-3.7.5.dist-info/entry_points.txt
ken_mcp-3.7.5.dist-info/licenses/LICENSE
ken_mcp-3.7.5.dist-info/RECORD
