Metadata-Version: 2.4
Name: ken-mcp
Version: 3.7.5
Summary: MCP server generator with modular architecture for creating FastMCP servers from natural language requirements
Project-URL: Homepage, https://github.com/ken-mcp/ken-mcp
Project-URL: Bug Reports, https://github.com/ken-mcp/ken-mcp/issues
Project-URL: Source, https://github.com/ken-mcp/ken-mcp
Author: KEN-MCP Contributors
License: MIT
License-File: LICENSE
Keywords: ai,fastmcp,generator,mcp,model-context-protocol
Classifier: Development Status :: 4 - Beta
Classifier: Intended Audience :: Developers
Classifier: License :: OSI Approved :: MIT License
Classifier: Programming Language :: Python :: 3
Classifier: Programming Language :: Python :: 3.8
Classifier: Programming Language :: Python :: 3.9
Classifier: Programming Language :: Python :: 3.10
Classifier: Programming Language :: Python :: 3.11
Classifier: Programming Language :: Python :: 3.12
Classifier: Topic :: Software Development :: Code Generators
Classifier: Topic :: Software Development :: Libraries :: Python Modules
Requires-Python: >=3.8
Requires-Dist: fastmcp>=0.1.0
Requires-Dist: httpx
Requires-Dist: pydantic
Provides-Extra: test
Requires-Dist: pytest-asyncio>=0.21.0; extra == 'test'
Requires-Dist: pytest-cov>=4.0.0; extra == 'test'
Requires-Dist: pytest-mock>=3.10.0; extra == 'test'
Requires-Dist: pytest>=7.0.0; extra == 'test'
